ktool/__init__.py
ktool/codesign.py
ktool/exceptions.py
ktool/generator.py
ktool/headers.py
ktool/image.py
ktool/kcache.py
ktool/ktool.py
ktool/ktool_script.py
ktool/loader.py
ktool/macho.py
ktool/objc.py
ktool/structs.py
ktool/swift.py
ktool/util.py
ktool/window.py
ktool_macho/__init__.py
ktool_macho/base.py
ktool_macho/binding.py
ktool_macho/codesign.py
ktool_macho/fixups.py
ktool_macho/load_commands.py
ktool_macho/mach_header.py
ktool_macho/structs.py
ktool_swift/__init__.py
ktool_swift/demangle.py
ktool_swift/structs.py
lib0cyn/__init__.py
lib0cyn/kplistlib.py
lib0cyn/log.py
lib0cyn/structs.py
k2l-2.0.0.dist-info/LICENSE
k2l-2.0.0.dist-info/METADATA
k2l-2.0.0.dist-info/WHEEL
k2l-2.0.0.dist-info/entry_points.txt
k2l-2.0.0.dist-info/RECORD
