Metadata-Version: 2.1
Name: k2l
Version: 2.0.0
Summary: Static MachO/ObjC Reverse Engineering Toolkit
Home-page: https://github.com/cxnder/ktool
License: MIT
Author: cynder
Author-email: kat@cynder.me
Requires-Python: >=3.6.2,<4.0.0
Classifier: License :: OSI Approved :: MIT License
Classifier: Programming Language :: Python :: 3
Classifier: Programming Language :: Python :: 3.7
Classifier: Programming Language :: Python :: 3.8
Classifier: Programming Language :: Python :: 3.9
Classifier: Programming Language :: Python :: 3.10
Classifier: Programming Language :: Python :: 3.11
Classifier: Programming Language :: Python :: 3.12
Requires-Dist: Pygments (>=2.11.2,<3.0.0)
Requires-Dist: kimg4 (>=0.1.1,<0.2.0)
Requires-Dist: pyaes (>=1.6.1,<2.0.0)
Requires-Dist: windows-curses (>=2.3.1,<3.0.0) ; sys_platform == "win32"
Project-URL: Repository, https://github.com/cxnder/ktool
